trd_utils/__init__.py
trd_utils/cipher/__init__.py
trd_utils/common_utils/float_utils.py
trd_utils/common_utils/httpx_utils.py
trd_utils/common_utils/wallet_utils.py
trd_utils/date_utils/__init__.py
trd_utils/date_utils/datetime_helpers.py
trd_utils/exchanges/README.md
trd_utils/exchanges/__init__.py
trd_utils/exchanges/base_types.py
trd_utils/exchanges/binance/__init__.py
trd_utils/exchanges/binance/binance_client.py
trd_utils/exchanges/binance/binance_types.py
trd_utils/exchanges/blofin/__init__.py
trd_utils/exchanges/blofin/blofin_client.py
trd_utils/exchanges/blofin/blofin_types.py
trd_utils/exchanges/bx_ultra/__init__.py
trd_utils/exchanges/bx_ultra/bx_types.py
trd_utils/exchanges/bx_ultra/bx_ultra_client.py
trd_utils/exchanges/bx_ultra/bx_utils.py
trd_utils/exchanges/errors.py
trd_utils/exchanges/exchange_base.py
trd_utils/exchanges/hyperliquid/README.md
trd_utils/exchanges/hyperliquid/__init__.py
trd_utils/exchanges/hyperliquid/hyperliquid_client.py
trd_utils/exchanges/hyperliquid/hyperliquid_types.py
trd_utils/exchanges/okx/__init__.py
trd_utils/exchanges/okx/okx_client.py
trd_utils/exchanges/okx/okx_types.py
trd_utils/exchanges/price_fetcher.py
trd_utils/html_utils/__init__.py
trd_utils/html_utils/html_formats.py
trd_utils/http_utils/__init__.py
trd_utils/http_utils/base_types.py
trd_utils/platforms/__init__.py
trd_utils/platforms/cr_bubbles/crb_client.py
trd_utils/platforms/cr_bubbles/crb_types.py
trd_utils/platforms/tradingview/__init__.py
trd_utils/platforms/tradingview/tradingview_client.py
trd_utils/platforms/tradingview/tradingview_types.py
trd_utils/types_helper/__init__.py
trd_utils/types_helper/base_model.py
trd_utils/types_helper/decorators.py
trd_utils/types_helper/model_config.py
trd_utils/types_helper/ultra_list.py
trd_utils/types_helper/utils.py
trd_utils-0.0.62.dist-info/METADATA
trd_utils-0.0.62.dist-info/WHEEL
trd_utils-0.0.62.dist-info/licenses/LICENSE
trd_utils-0.0.62.dist-info/RECORD
